inaFaceAnalyzer/__init__.py
inaFaceAnalyzer/_version.py
inaFaceAnalyzer/commandline_utils.py
inaFaceAnalyzer/display_utils.py
inaFaceAnalyzer/excel_export.py
inaFaceAnalyzer/face_alignment.py
inaFaceAnalyzer/face_classifier.py
inaFaceAnalyzer/face_detector.py
inaFaceAnalyzer/face_extractor.py
inaFaceAnalyzer/face_preprocessing.py
inaFaceAnalyzer/face_tracking.py
inaFaceAnalyzer/inaFaceAnalyzer.py
inaFaceAnalyzer/keras_vggface_patch.py
inaFaceAnalyzer/libfacedetection_priorbox.py
inaFaceAnalyzer/notebook_utils.py
inaFaceAnalyzer/opencv_utils.py
inaFaceAnalyzer/pyav_utils.py
inaFaceAnalyzer/rect.py
inaFaceAnalyzer/remote_utils.py
inaFaceAnalyzer/svm_utils.py
inaFaceAnalyzer/template.ass
inaFaceAnalyzer-0.6.3.data/data/LICENSE
inaFaceAnalyzer-0.6.3.data/scripts/ina_face_analyzer.py
inaFaceAnalyzer-0.6.3.data/scripts/ina_face_analyzer_distributed_server.py
inaFaceAnalyzer-0.6.3.data/scripts/ina_face_analyzer_distributed_worker.py
inaFaceAnalyzer-0.6.3.data/scripts/ina_face_analyzer_webcam_demo.py
inaFaceAnalyzer-0.6.3.dist-info/LICENSE
inaFaceAnalyzer-0.6.3.dist-info/METADATA
inaFaceAnalyzer-0.6.3.dist-info/WHEEL
inaFaceAnalyzer-0.6.3.dist-info/top_level.txt
inaFaceAnalyzer-0.6.3.dist-info/RECORD
