Metadata-Version: 2.1
Name: inaFaceAnalyzer
Version: 0.6.3
Summary: inaFaceAnalyzer is a Python toolbox for large-scale face-based analysis of image and video streams. It provides fast API and command line programs allowing to perform face detection, face tracking, gender and age prediction, and export to CSV or rich ASS subtitles
Home-page: https://github.com/ina-foss/inaFaceAnalyzer
Author: David Doukhan, Zohra Rezgui, Thomas Petit
Author-email: david.doukhan@gmail.com, zohra.rzg@gmail.com, tpetit@ina.fr
License: MIT
Keywords: gender-equality,gender-classification
Classifier: Development Status :: 3 - Alpha
Classifier: Intended Audience :: Developers
Classifier: Intended Audience :: Education
Classifier: Intended Audience :: Science/Research
Classifier: License :: OSI Approved :: MIT License
Classifier: Operating System :: OS Independent
Classifier: Programming Language :: Python :: 3
Classifier: Programming Language :: Python :: 3 :: Only
Classifier: Programming Language :: Python :: 3.7
Classifier: Programming Language :: Python :: 3.8
Classifier: Programming Language :: Python :: 3.9
Classifier: Topic :: Multimedia :: Video
Classifier: Topic :: Scientific/Engineering
Classifier: Topic :: Scientific/Engineering :: Artificial Intelligence
Classifier: Topic :: Scientific/Engineering :: Image Processing
Classifier: Topic :: Scientific/Engineering :: Image Recognition
Classifier: Topic :: Sociology
Classifier: Topic :: Software Development
Classifier: Topic :: Software Development :: Libraries
Classifier: Topic :: Software Development :: Libraries :: Python Modules
Classifier: Topic :: Sociology
Requires-Python: >=3.7
License-File: LICENSE
Requires-Dist: opencv-contrib-python
Requires-Dist: dlib
Requires-Dist: pandas
Requires-Dist: scikit-learn
Requires-Dist: h5py
Requires-Dist: matplotlib
Requires-Dist: onnxruntime-gpu
Requires-Dist: cheetah3
Requires-Dist: av
Requires-Dist: tensorflow <2.16.0,>=2.6
Requires-Dist: pyro4
Requires-Dist: xlsxwriter
Provides-Extra: doc
Requires-Dist: sphinx-toolbox ; extra == 'doc'
